{
  "root": true,
  "title": "Security",
  "description": "Ryu's security model: the trust boundary, sandboxing, command approval and HITL, credential and environment scrubbing, outbound DLP, SSRF protection, network binding and token auth, channel allowlists, and a deployment hardening checklist.",
  "icon": "ShieldCheck",
  "pages": [
    "index",
    "---Model---",
    "trust-model",
    "---Access Control---",
    "permissions",
    "command-approval",
    "---Isolation---",
    "sandboxing-isolation",
    "---Data Protection---",
    "credential-scrubbing",
    "outbound-dlp",
    "---Network---",
    "ssrf-protection",
    "network-binding-auth",
    "channel-allowlists",
    "---Deployment---",
    "hardening-checklist"
  ]
}
